{
	"files": [
		{
			"name": "HighPassFilter_frag",
			"files": [
				"HighPassFilter.frag.essl",
				"HighPassFilter-webgl2.frag.essl"
			],
			"file_sizes": [
				1
			],
			"type": "shader",
			"inputs": [
				{
					"name": "texCoord",
					"type": "vec2"
				}
			],
			"outputs": [
				{
					"name": "FragColor",
					"type": "vec4"
				}
			],
			"uniforms": [
				{
					"name": "tex",
					"type": "sampler2D"
				},
				{
					"name": "brightIndex",
					"type": "vec3"
				},
				{
					"name": "tolerance",
					"type": "float"
				},
				{
					"name": "darkColor",
					"type": "vec3"
				},
				{
					"name": "tintColor",
					"type": "vec3"
				}
			],
			"types": []
		},
		{
			"name": "Kenney_Thick",
			"files": [
				"Kenney Thick.ttf"
			],
			"file_sizes": [
				9448
			],
			"type": "font"
		},
		{
			"name": "ShBrightness_frag",
			"files": [
				"ShBrightness.frag.essl",
				"ShBrightness-webgl2.frag.essl"
			],
			"file_sizes": [
				1
			],
			"type": "shader",
			"inputs": [
				{
					"name": "texCoord",
					"type": "vec2"
				}
			],
			"outputs": [
				{
					"name": "color",
					"type": "vec4"
				}
			],
			"uniforms": [
				{
					"name": "tex",
					"type": "sampler2D"
				},
				{
					"name": "brightness",
					"type": "float"
				}
			],
			"types": []
		},
		{
			"name": "alpha_vert",
			"files": [
				"alpha.vert.essl",
				"alpha-webgl2.vert.essl"
			],
			"file_sizes": [
				1
			],
			"type": "shader",
			"inputs": [
				{
					"name": "vertexPosition",
					"type": "vec3"
				},
				{
					"name": "texPosition",
					"type": "vec2"
				},
				{
					"name": "gl_VertexID",
					"type": "int"
				},
				{
					"name": "gl_InstanceID",
					"type": "int"
				}
			],
			"outputs": [
				{
					"name": "texCoord",
					"type": "vec3"
				}
			],
			"uniforms": [
				{
					"name": "projectionMatrix",
					"type": "mat4"
				},
				{
					"name": "alpha",
					"type": "float"
				}
			],
			"types": [
				{
					"name": "gl_PerVertex",
					"members": [
						{
							"type": "vec4",
							"name": "gl_Position"
						},
						{
							"type": "float",
							"name": "gl_PointSize"
						},
						{
							"type": "float[]",
							"name": "gl_ClipDistance"
						},
						{
							"type": "float[]",
							"name": "gl_CullDistance"
						}
					]
				}
			]
		},
		{
			"name": "ball",
			"files": [
				"ball.png"
			],
			"file_sizes": [
				469
			],
			"type": "image",
			"original_width": 40,
			"original_height": 40
		},
		{
			"name": "blurFragmentShader_frag",
			"files": [
				"blurFragmentShader.frag.essl",
				"blurFragmentShader-webgl2.frag.essl"
			],
			"file_sizes": [
				1
			],
			"type": "shader",
			"inputs": [
				{
					"name": "v_blurCoord2",
					"type": "vec2"
				},
				{
					"name": "v_texCoord",
					"type": "vec2"
				},
				{
					"name": "v_blurCoord0",
					"type": "vec2"
				},
				{
					"name": "v_blurCoord1",
					"type": "vec2"
				},
				{
					"name": "v_blurCoord3",
					"type": "vec2"
				},
				{
					"name": "v_blurCoord4",
					"type": "vec2"
				},
				{
					"name": "v_blurCoord5",
					"type": "vec2"
				}
			],
			"outputs": [
				{
					"name": "color",
					"type": "vec4"
				}
			],
			"uniforms": [
				{
					"name": "tex",
					"type": "sampler2D"
				}
			],
			"types": []
		},
		{
			"name": "blur_pass_frag",
			"files": [
				"blur_pass.frag.essl",
				"blur_pass-webgl2.frag.essl"
			],
			"file_sizes": [
				1
			],
			"type": "shader",
			"inputs": [
				{
					"name": "texCoord",
					"type": "vec2"
				}
			],
			"outputs": [
				{
					"name": "fragColor",
					"type": "vec4"
				}
			],
			"uniforms": [
				{
					"name": "tex",
					"type": "sampler2D"
				},
				{
					"name": "dirInv",
					"type": "vec2"
				}
			],
			"types": []
		},
		{
			"name": "cannon",
			"files": [
				"cannon.png"
			],
			"file_sizes": [
				36798
			],
			"type": "image",
			"original_width": 459,
			"original_height": 459
		},
		{
			"name": "filmGrain_frag",
			"files": [
				"filmGrain.frag.essl",
				"filmGrain-webgl2.frag.essl"
			],
			"file_sizes": [
				1
			],
			"type": "shader",
			"inputs": [
				{
					"name": "texCoord",
					"type": "vec2"
				}
			],
			"outputs": [
				{
					"name": "FragColor",
					"type": "vec4"
				}
			],
			"uniforms": [
				{
					"name": "resolution",
					"type": "vec2"
				},
				{
					"name": "tex",
					"type": "sampler2D"
				}
			],
			"types": []
		},
		{
			"name": "fov_frag",
			"files": [
				"fov.frag.essl",
				"fov-webgl2.frag.essl"
			],
			"file_sizes": [
				1
			],
			"type": "shader",
			"inputs": [
				{
					"name": "texCoord",
					"type": "vec2"
				}
			],
			"outputs": [
				{
					"name": "FragColor",
					"type": "vec4"
				}
			],
			"uniforms": [
				{
					"name": "gbufferD",
					"type": "sampler2D"
				},
				{
					"name": "tex",
					"type": "sampler2D"
				}
			],
			"types": []
		},
		{
			"name": "fxaa_frag",
			"files": [
				"fxaa.frag.essl",
				"fxaa-webgl2.frag.essl"
			],
			"file_sizes": [
				1
			],
			"type": "shader",
			"inputs": [
				{
					"name": "texCoord",
					"type": "vec2"
				}
			],
			"outputs": [
				{
					"name": "fragColor",
					"type": "vec4"
				}
			],
			"uniforms": [
				{
					"name": "screenSizeInv",
					"type": "vec2"
				},
				{
					"name": "tex",
					"type": "sampler2D"
				}
			],
			"types": []
		},
		{
			"name": "gameOver",
			"files": [
				"gameOver.png"
			],
			"file_sizes": [
				17088
			],
			"type": "image",
			"original_width": 231,
			"original_height": 244
		},
		{
			"name": "grass",
			"files": [
				"grass.png"
			],
			"file_sizes": [
				2309
			],
			"type": "image",
			"original_width": 127,
			"original_height": 120
		},
		{
			"name": "hBlurVertexShader_vert",
			"files": [
				"hBlurVertexShader.vert.essl",
				"hBlurVertexShader-webgl2.vert.essl"
			],
			"file_sizes": [
				1
			],
			"type": "shader",
			"inputs": [
				{
					"name": "vertexPosition",
					"type": "vec3"
				},
				{
					"name": "texPosition",
					"type": "vec2"
				},
				{
					"name": "gl_VertexID",
					"type": "int"
				},
				{
					"name": "gl_InstanceID",
					"type": "int"
				}
			],
			"outputs": [
				{
					"name": "v_texCoord",
					"type": "vec2"
				},
				{
					"name": "v_blurCoord0",
					"type": "vec2"
				},
				{
					"name": "v_blurCoord1",
					"type": "vec2"
				},
				{
					"name": "v_blurCoord2",
					"type": "vec2"
				},
				{
					"name": "v_blurCoord3",
					"type": "vec2"
				},
				{
					"name": "v_blurCoord4",
					"type": "vec2"
				},
				{
					"name": "v_blurCoord5",
					"type": "vec2"
				}
			],
			"uniforms": [
				{
					"name": "projectionMatrix",
					"type": "mat4"
				},
				{
					"name": "resolution",
					"type": "vec2"
				}
			],
			"types": [
				{
					"name": "gl_PerVertex",
					"members": [
						{
							"type": "vec4",
							"name": "gl_Position"
						},
						{
							"type": "float",
							"name": "gl_PointSize"
						},
						{
							"type": "float[]",
							"name": "gl_ClipDistance"
						},
						{
							"type": "float[]",
							"name": "gl_CullDistance"
						}
					]
				}
			]
		},
		{
			"name": "jason",
			"files": [
				"jason.png"
			],
			"file_sizes": [
				14448
			],
			"type": "image",
			"original_width": 120,
			"original_height": 362
		},
		{
			"name": "jason_xml",
			"files": [
				"jason.xml"
			],
			"file_sizes": [
				3260
			],
			"type": "blob"
		},
		{
			"name": "julia",
			"files": [
				"julia.png"
			],
			"file_sizes": [
				14731
			],
			"type": "image",
			"original_width": 237,
			"original_height": 167
		},
		{
			"name": "julia_xml",
			"files": [
				"julia.xml"
			],
			"file_sizes": [
				4883
			],
			"type": "blob"
		},
		{
			"name": "mainfont",
			"files": [
				"mainfont.ttf"
			],
			"file_sizes": [
				91504
			],
			"type": "font"
		},
		{
			"name": "meshBones_vert",
			"files": [
				"meshBones.vert.essl",
				"meshBones-webgl2.vert.essl"
			],
			"file_sizes": [
				1
			],
			"type": "shader",
			"inputs": [
				{
					"name": "boneIndex",
					"type": "vec4"
				},
				{
					"name": "pos",
					"type": "vec3"
				},
				{
					"name": "weights",
					"type": "vec4"
				},
				{
					"name": "normal",
					"type": "vec3"
				},
				{
					"name": "uv",
					"type": "vec2"
				},
				{
					"name": "gl_VertexID",
					"type": "int"
				},
				{
					"name": "gl_InstanceID",
					"type": "int"
				}
			],
			"outputs": [
				{
					"name": "texCoord",
					"type": "vec2"
				}
			],
			"uniforms": [
				{
					"name": "bones",
					"type": "mat4[]"
				},
				{
					"name": "projection",
					"type": "mat4"
				},
				{
					"name": "view",
					"type": "mat4"
				},
				{
					"name": "model",
					"type": "mat4"
				}
			],
			"types": [
				{
					"name": "gl_PerVertex",
					"members": [
						{
							"type": "vec4",
							"name": "gl_Position"
						},
						{
							"type": "float",
							"name": "gl_PointSize"
						},
						{
							"type": "float[]",
							"name": "gl_ClipDistance"
						},
						{
							"type": "float[]",
							"name": "gl_CullDistance"
						}
					]
				}
			]
		},
		{
			"name": "meshNoShade_frag",
			"files": [
				"meshNoShade.frag.essl",
				"meshNoShade-webgl2.frag.essl"
			],
			"file_sizes": [
				1
			],
			"type": "shader",
			"inputs": [
				{
					"name": "texCoord",
					"type": "vec2"
				}
			],
			"outputs": [
				{
					"name": "color",
					"type": "vec4"
				}
			],
			"uniforms": [
				{
					"name": "tex",
					"type": "sampler2D"
				}
			],
			"types": []
		},
		{
			"name": "mesh_frag",
			"files": [
				"mesh.frag.essl",
				"mesh-webgl2.frag.essl"
			],
			"file_sizes": [
				1
			],
			"type": "shader",
			"inputs": [
				{
					"name": "texCoord",
					"type": "vec2"
				},
				{
					"name": "norm",
					"type": "vec3"
				}
			],
			"outputs": [
				{
					"name": "color",
					"type": "vec4"
				}
			],
			"uniforms": [
				{
					"name": "tex",
					"type": "sampler2D"
				}
			],
			"types": []
		},
		{
			"name": "mesh_vert",
			"files": [
				"mesh.vert.essl",
				"mesh-webgl2.vert.essl"
			],
			"file_sizes": [
				1
			],
			"type": "shader",
			"inputs": [
				{
					"name": "uv",
					"type": "vec2"
				},
				{
					"name": "pos",
					"type": "vec3"
				},
				{
					"name": "normal",
					"type": "vec3"
				},
				{
					"name": "gl_VertexID",
					"type": "int"
				},
				{
					"name": "gl_InstanceID",
					"type": "int"
				}
			],
			"outputs": [
				{
					"name": "texCoord",
					"type": "vec2"
				}
			],
			"uniforms": [
				{
					"name": "mvp",
					"type": "mat4"
				}
			],
			"types": [
				{
					"name": "gl_PerVertex",
					"members": [
						{
							"type": "vec4",
							"name": "gl_Position"
						},
						{
							"type": "float",
							"name": "gl_PointSize"
						},
						{
							"type": "float[]",
							"name": "gl_ClipDistance"
						},
						{
							"type": "float[]",
							"name": "gl_CullDistance"
						}
					]
				}
			]
		},
		{
			"name": "mirage_frag",
			"files": [
				"mirage.frag.essl",
				"mirage-webgl2.frag.essl"
			],
			"file_sizes": [
				1
			],
			"type": "shader",
			"inputs": [
				{
					"name": "texCoord",
					"type": "vec2"
				}
			],
			"outputs": [
				{
					"name": "FragColor",
					"type": "vec4"
				}
			],
			"uniforms": [
				{
					"name": "tex",
					"type": "sampler2D"
				},
				{
					"name": "time",
					"type": "float"
				}
			],
			"types": []
		},
		{
			"name": "mosaic_frag",
			"files": [
				"mosaic.frag.essl",
				"mosaic-webgl2.frag.essl"
			],
			"file_sizes": [
				1
			],
			"type": "shader",
			"inputs": [
				{
					"name": "texCoord",
					"type": "vec2"
				}
			],
			"outputs": [
				{
					"name": "FragColor",
					"type": "vec4"
				}
			],
			"uniforms": [
				{
					"name": "tiles",
					"type": "float"
				},
				{
					"name": "tex",
					"type": "sampler2D"
				}
			],
			"types": []
		},
		{
			"name": "multiplyColor_frag",
			"files": [
				"multiplyColor.frag.essl",
				"multiplyColor-webgl2.frag.essl"
			],
			"file_sizes": [
				1
			],
			"type": "shader",
			"inputs": [
				{
					"name": "texCoord",
					"type": "vec2"
				}
			],
			"outputs": [
				{
					"name": "FragColor",
					"type": "vec4"
				}
			],
			"uniforms": [
				{
					"name": "tex",
					"type": "sampler2D"
				},
				{
					"name": "colorMul",
					"type": "vec4"
				}
			],
			"types": []
		},
		{
			"name": "outline_frag",
			"files": [
				"outline.frag.essl",
				"outline-webgl2.frag.essl"
			],
			"file_sizes": [
				1
			],
			"type": "shader",
			"inputs": [
				{
					"name": "texCoord",
					"type": "vec2"
				}
			],
			"outputs": [
				{
					"name": "FragColor",
					"type": "vec4"
				}
			],
			"uniforms": [
				{
					"name": "tex",
					"type": "sampler2D"
				},
				{
					"name": "stepSize",
					"type": "vec2"
				},
				{
					"name": "color",
					"type": "vec3"
				}
			],
			"types": []
		},
		{
			"name": "painter_colored_frag",
			"files": [
				"painter-colored.frag.essl",
				"painter-colored-webgl2.frag.essl"
			],
			"file_sizes": [
				1
			],
			"type": "shader",
			"inputs": [
				{
					"name": "fragmentColor",
					"type": "vec4"
				}
			],
			"outputs": [
				{
					"name": "FragColor",
					"type": "vec4"
				}
			],
			"uniforms": [],
			"types": []
		},
		{
			"name": "painter_colored_vert",
			"files": [
				"painter-colored.vert.essl",
				"painter-colored-webgl2.vert.essl"
			],
			"file_sizes": [
				1
			],
			"type": "shader",
			"inputs": [
				{
					"name": "vertexPosition",
					"type": "vec3"
				},
				{
					"name": "vertexColor",
					"type": "vec4"
				},
				{
					"name": "gl_VertexID",
					"type": "int"
				},
				{
					"name": "gl_InstanceID",
					"type": "int"
				}
			],
			"outputs": [
				{
					"name": "fragmentColor",
					"type": "vec4"
				}
			],
			"uniforms": [
				{
					"name": "projectionMatrix",
					"type": "mat4"
				}
			],
			"types": [
				{
					"name": "gl_PerVertex",
					"members": [
						{
							"type": "vec4",
							"name": "gl_Position"
						},
						{
							"type": "float",
							"name": "gl_PointSize"
						},
						{
							"type": "float[]",
							"name": "gl_ClipDistance"
						},
						{
							"type": "float[]",
							"name": "gl_CullDistance"
						}
					]
				}
			]
		},
		{
			"name": "painter_image_frag",
			"files": [
				"painter-image.frag.essl",
				"painter-image-webgl2.frag.essl"
			],
			"file_sizes": [
				1
			],
			"type": "shader",
			"inputs": [
				{
					"name": "texCoord",
					"type": "vec2"
				},
				{
					"name": "color",
					"type": "vec4"
				}
			],
			"outputs": [
				{
					"name": "FragColor",
					"type": "vec4"
				}
			],
			"uniforms": [
				{
					"name": "tex",
					"type": "sampler2D"
				}
			],
			"types": []
		},
		{
			"name": "painter_image_vert",
			"files": [
				"painter-image.vert.essl",
				"painter-image-webgl2.vert.essl"
			],
			"file_sizes": [
				1
			],
			"type": "shader",
			"inputs": [
				{
					"name": "vertexPosition",
					"type": "vec3"
				},
				{
					"name": "texPosition",
					"type": "vec2"
				},
				{
					"name": "vertexColor",
					"type": "vec4"
				},
				{
					"name": "gl_VertexID",
					"type": "int"
				},
				{
					"name": "gl_InstanceID",
					"type": "int"
				}
			],
			"outputs": [
				{
					"name": "texCoord",
					"type": "vec2"
				},
				{
					"name": "color",
					"type": "vec4"
				}
			],
			"uniforms": [
				{
					"name": "projectionMatrix",
					"type": "mat4"
				}
			],
			"types": [
				{
					"name": "gl_PerVertex",
					"members": [
						{
							"type": "vec4",
							"name": "gl_Position"
						},
						{
							"type": "float",
							"name": "gl_PointSize"
						},
						{
							"type": "float[]",
							"name": "gl_ClipDistance"
						},
						{
							"type": "float[]",
							"name": "gl_CullDistance"
						}
					]
				}
			]
		},
		{
			"name": "painter_text_frag",
			"files": [
				"painter-text.frag.essl",
				"painter-text-webgl2.frag.essl"
			],
			"file_sizes": [
				1
			],
			"type": "shader",
			"inputs": [
				{
					"name": "fragmentColor",
					"type": "vec4"
				},
				{
					"name": "texCoord",
					"type": "vec2"
				}
			],
			"outputs": [
				{
					"name": "FragColor",
					"type": "vec4"
				}
			],
			"uniforms": [
				{
					"name": "tex",
					"type": "sampler2D"
				}
			],
			"types": []
		},
		{
			"name": "painter_text_vert",
			"files": [
				"painter-text.vert.essl",
				"painter-text-webgl2.vert.essl"
			],
			"file_sizes": [
				1
			],
			"type": "shader",
			"inputs": [
				{
					"name": "vertexPosition",
					"type": "vec3"
				},
				{
					"name": "texPosition",
					"type": "vec2"
				},
				{
					"name": "vertexColor",
					"type": "vec4"
				},
				{
					"name": "gl_VertexID",
					"type": "int"
				},
				{
					"name": "gl_InstanceID",
					"type": "int"
				}
			],
			"outputs": [
				{
					"name": "texCoord",
					"type": "vec2"
				},
				{
					"name": "fragmentColor",
					"type": "vec4"
				}
			],
			"uniforms": [
				{
					"name": "projectionMatrix",
					"type": "mat4"
				}
			],
			"types": [
				{
					"name": "gl_PerVertex",
					"members": [
						{
							"type": "vec4",
							"name": "gl_Position"
						},
						{
							"type": "float",
							"name": "gl_PointSize"
						},
						{
							"type": "float[]",
							"name": "gl_ClipDistance"
						},
						{
							"type": "float[]",
							"name": "gl_CullDistance"
						}
					]
				}
			]
		},
		{
			"name": "painter_video_frag",
			"files": [
				"painter-video.frag.essl",
				"painter-video-webgl2.frag.essl"
			],
			"file_sizes": [
				1
			],
			"type": "shader",
			"inputs": [
				{
					"name": "texCoord",
					"type": "vec2"
				},
				{
					"name": "color",
					"type": "vec4"
				}
			],
			"outputs": [
				{
					"name": "FragColor",
					"type": "vec4"
				}
			],
			"uniforms": [
				{
					"name": "tex",
					"type": "sampler2D"
				}
			],
			"types": []
		},
		{
			"name": "painter_video_vert",
			"files": [
				"painter-video.vert.essl",
				"painter-video-webgl2.vert.essl"
			],
			"file_sizes": [
				1
			],
			"type": "shader",
			"inputs": [
				{
					"name": "vertexPosition",
					"type": "vec3"
				},
				{
					"name": "texPosition",
					"type": "vec2"
				},
				{
					"name": "vertexColor",
					"type": "vec4"
				},
				{
					"name": "gl_VertexID",
					"type": "int"
				},
				{
					"name": "gl_InstanceID",
					"type": "int"
				}
			],
			"outputs": [
				{
					"name": "texCoord",
					"type": "vec2"
				},
				{
					"name": "color",
					"type": "vec4"
				}
			],
			"uniforms": [
				{
					"name": "projectionMatrix",
					"type": "mat4"
				}
			],
			"types": [
				{
					"name": "gl_PerVertex",
					"members": [
						{
							"type": "vec4",
							"name": "gl_Position"
						},
						{
							"type": "float",
							"name": "gl_PointSize"
						},
						{
							"type": "float[]",
							"name": "gl_ClipDistance"
						},
						{
							"type": "float[]",
							"name": "gl_CullDistance"
						}
					]
				}
			]
		},
		{
			"name": "poly_frag",
			"files": [
				"poly.frag.essl",
				"poly-webgl2.frag.essl"
			],
			"file_sizes": [
				1
			],
			"type": "shader",
			"inputs": [],
			"outputs": [
				{
					"name": "FragColor",
					"type": "vec4"
				}
			],
			"uniforms": [
				{
					"name": "color",
					"type": "vec4"
				}
			],
			"types": []
		},
		{
			"name": "poly_vert",
			"files": [
				"poly.vert.essl",
				"poly-webgl2.vert.essl"
			],
			"file_sizes": [
				1
			],
			"type": "shader",
			"inputs": [
				{
					"name": "vertexPosition",
					"type": "vec3"
				},
				{
					"name": "gl_VertexID",
					"type": "int"
				},
				{
					"name": "gl_InstanceID",
					"type": "int"
				}
			],
			"outputs": [],
			"uniforms": [
				{
					"name": "projectionMatrix",
					"type": "mat4"
				}
			],
			"types": [
				{
					"name": "gl_PerVertex",
					"members": [
						{
							"type": "vec4",
							"name": "gl_Position"
						},
						{
							"type": "float",
							"name": "gl_PointSize"
						},
						{
							"type": "float[]",
							"name": "gl_ClipDistance"
						},
						{
							"type": "float[]",
							"name": "gl_CullDistance"
						}
					]
				}
			]
		},
		{
			"name": "renderAreaTint_frag",
			"files": [
				"renderAreaTint.frag.essl",
				"renderAreaTint-webgl2.frag.essl"
			],
			"file_sizes": [
				1
			],
			"type": "shader",
			"inputs": [
				{
					"name": "texCoord",
					"type": "vec2"
				}
			],
			"outputs": [
				{
					"name": "FragColor",
					"type": "vec4"
				}
			],
			"uniforms": [
				{
					"name": "tex",
					"type": "sampler2D"
				}
			],
			"types": []
		},
		{
			"name": "rgbSplit_frag",
			"files": [
				"rgbSplit.frag.essl",
				"rgbSplit-webgl2.frag.essl"
			],
			"file_sizes": [
				1
			],
			"type": "shader",
			"inputs": [
				{
					"name": "texCoord",
					"type": "vec2"
				}
			],
			"outputs": [
				{
					"name": "FragColor",
					"type": "vec4"
				}
			],
			"uniforms": [
				{
					"name": "tex",
					"type": "sampler2D"
				},
				{
					"name": "time",
					"type": "float"
				}
			],
			"types": []
		},
		{
			"name": "shInverseMask_frag",
			"files": [
				"shInverseMask.frag.essl",
				"shInverseMask-webgl2.frag.essl"
			],
			"file_sizes": [
				1
			],
			"type": "shader",
			"inputs": [
				{
					"name": "texCoord",
					"type": "vec2"
				},
				{
					"name": "texCoordMask",
					"type": "vec2"
				}
			],
			"outputs": [
				{
					"name": "FragColor",
					"type": "vec4"
				}
			],
			"uniforms": [
				{
					"name": "tex",
					"type": "sampler2D"
				},
				{
					"name": "mask",
					"type": "sampler2D"
				}
			],
			"types": []
		},
		{
			"name": "shMask_frag",
			"files": [
				"shMask.frag.essl",
				"shMask-webgl2.frag.essl"
			],
			"file_sizes": [
				1
			],
			"type": "shader",
			"inputs": [
				{
					"name": "texCoord",
					"type": "vec2"
				},
				{
					"name": "texCoordMask",
					"type": "vec2"
				}
			],
			"outputs": [
				{
					"name": "FragColor",
					"type": "vec4"
				}
			],
			"uniforms": [
				{
					"name": "tex",
					"type": "sampler2D"
				},
				{
					"name": "mask",
					"type": "sampler2D"
				}
			],
			"types": []
		},
		{
			"name": "shMask_vert",
			"files": [
				"shMask.vert.essl",
				"shMask-webgl2.vert.essl"
			],
			"file_sizes": [
				1
			],
			"type": "shader",
			"inputs": [
				{
					"name": "vertexPosition",
					"type": "vec3"
				},
				{
					"name": "texPosition",
					"type": "vec2"
				},
				{
					"name": "gl_VertexID",
					"type": "int"
				},
				{
					"name": "gl_InstanceID",
					"type": "int"
				}
			],
			"outputs": [
				{
					"name": "texCoord",
					"type": "vec2"
				},
				{
					"name": "texCoordMask",
					"type": "vec2"
				}
			],
			"uniforms": [
				{
					"name": "projectionMatrix",
					"type": "mat4"
				}
			],
			"types": [
				{
					"name": "gl_PerVertex",
					"members": [
						{
							"type": "vec4",
							"name": "gl_Position"
						},
						{
							"type": "float",
							"name": "gl_PointSize"
						},
						{
							"type": "float[]",
							"name": "gl_ClipDistance"
						},
						{
							"type": "float[]",
							"name": "gl_CullDistance"
						}
					]
				}
			]
		},
		{
			"name": "shMaxBlend_frag",
			"files": [
				"shMaxBlend.frag.essl",
				"shMaxBlend-webgl2.frag.essl"
			],
			"file_sizes": [
				1
			],
			"type": "shader",
			"inputs": [
				{
					"name": "texCoord",
					"type": "vec2"
				},
				{
					"name": "texCoordMask",
					"type": "vec2"
				}
			],
			"outputs": [
				{
					"name": "FragColor",
					"type": "vec4"
				}
			],
			"uniforms": [
				{
					"name": "tex",
					"type": "sampler2D"
				},
				{
					"name": "mask",
					"type": "sampler2D"
				}
			],
			"types": []
		},
		{
			"name": "shMixGlow_frag",
			"files": [
				"shMixGlow.frag.essl",
				"shMixGlow-webgl2.frag.essl"
			],
			"file_sizes": [
				1
			],
			"type": "shader",
			"inputs": [
				{
					"name": "texCoord",
					"type": "vec2"
				}
			],
			"outputs": [
				{
					"name": "FragColor",
					"type": "vec4"
				}
			],
			"uniforms": [
				{
					"name": "tex",
					"type": "sampler2D"
				},
				{
					"name": "baseColor",
					"type": "sampler2D"
				},
				{
					"name": "amount",
					"type": "float"
				}
			],
			"types": []
		},
		{
			"name": "simpleAlpha_frag",
			"files": [
				"simpleAlpha.frag.essl",
				"simpleAlpha-webgl2.frag.essl"
			],
			"file_sizes": [
				1
			],
			"type": "shader",
			"inputs": [
				{
					"name": "texCoord",
					"type": "vec3"
				}
			],
			"outputs": [
				{
					"name": "FragColor",
					"type": "vec4"
				}
			],
			"uniforms": [
				{
					"name": "tex",
					"type": "sampler2D"
				}
			],
			"types": []
		},
		{
			"name": "simpleAlpha_vert",
			"files": [
				"simpleAlpha.vert.essl",
				"simpleAlpha-webgl2.vert.essl"
			],
			"file_sizes": [
				1
			],
			"type": "shader",
			"inputs": [
				{
					"name": "vertexPosition",
					"type": "vec3"
				},
				{
					"name": "texPosition",
					"type": "vec3"
				},
				{
					"name": "gl_VertexID",
					"type": "int"
				},
				{
					"name": "gl_InstanceID",
					"type": "int"
				}
			],
			"outputs": [
				{
					"name": "texCoord",
					"type": "vec3"
				}
			],
			"uniforms": [
				{
					"name": "projectionMatrix",
					"type": "mat4"
				}
			],
			"types": [
				{
					"name": "gl_PerVertex",
					"members": [
						{
							"type": "vec4",
							"name": "gl_Position"
						},
						{
							"type": "float",
							"name": "gl_PointSize"
						},
						{
							"type": "float[]",
							"name": "gl_ClipDistance"
						},
						{
							"type": "float[]",
							"name": "gl_CullDistance"
						}
					]
				}
			]
		},
		{
			"name": "simpleColorTransformation_frag",
			"files": [
				"simpleColorTransformation.frag.essl",
				"simpleColorTransformation-webgl2.frag.essl"
			],
			"file_sizes": [
				1
			],
			"type": "shader",
			"inputs": [
				{
					"name": "texCoord",
					"type": "vec2"
				},
				{
					"name": "_colorMul",
					"type": "vec4"
				},
				{
					"name": "_colorAdd",
					"type": "vec4"
				}
			],
			"outputs": [
				{
					"name": "FragColor",
					"type": "vec4"
				}
			],
			"uniforms": [
				{
					"name": "tex",
					"type": "sampler2D"
				}
			],
			"types": []
		},
		{
			"name": "simpleColorTransformation_vert",
			"files": [
				"simpleColorTransformation.vert.essl",
				"simpleColorTransformation-webgl2.vert.essl"
			],
			"file_sizes": [
				1
			],
			"type": "shader",
			"inputs": [
				{
					"name": "vertexPosition",
					"type": "vec3"
				},
				{
					"name": "texPosition",
					"type": "vec2"
				},
				{
					"name": "colorMul",
					"type": "vec4"
				},
				{
					"name": "colorAdd",
					"type": "vec4"
				},
				{
					"name": "gl_VertexID",
					"type": "int"
				},
				{
					"name": "gl_InstanceID",
					"type": "int"
				}
			],
			"outputs": [
				{
					"name": "texCoord",
					"type": "vec2"
				},
				{
					"name": "_colorMul",
					"type": "vec4"
				},
				{
					"name": "_colorAdd",
					"type": "vec4"
				}
			],
			"uniforms": [
				{
					"name": "projectionMatrix",
					"type": "mat4"
				}
			],
			"types": [
				{
					"name": "gl_PerVertex",
					"members": [
						{
							"type": "vec4",
							"name": "gl_Position"
						},
						{
							"type": "float",
							"name": "gl_PointSize"
						},
						{
							"type": "float[]",
							"name": "gl_ClipDistance"
						},
						{
							"type": "float[]",
							"name": "gl_CullDistance"
						}
					]
				}
			]
		},
		{
			"name": "simpleLight_frag",
			"files": [
				"simpleLight.frag.essl",
				"simpleLight-webgl2.frag.essl"
			],
			"file_sizes": [
				1
			],
			"type": "shader",
			"inputs": [
				{
					"name": "texCoord",
					"type": "vec2"
				}
			],
			"outputs": [
				{
					"name": "FragColor",
					"type": "vec4"
				}
			],
			"uniforms": [
				{
					"name": "tex",
					"type": "sampler2D"
				},
				{
					"name": "tex2",
					"type": "sampler2D"
				}
			],
			"types": []
		},
		{
			"name": "simpleRgbSplit_frag",
			"files": [
				"simpleRgbSplit.frag.essl",
				"simpleRgbSplit-webgl2.frag.essl"
			],
			"file_sizes": [
				1
			],
			"type": "shader",
			"inputs": [
				{
					"name": "texCoord",
					"type": "vec2"
				}
			],
			"outputs": [
				{
					"name": "FragColor",
					"type": "vec4"
				}
			],
			"uniforms": [
				{
					"name": "resolution",
					"type": "vec2"
				},
				{
					"name": "tex",
					"type": "sampler2D"
				}
			],
			"types": []
		},
		{
			"name": "simpleTime_vert",
			"files": [
				"simpleTime.vert.essl",
				"simpleTime-webgl2.vert.essl"
			],
			"file_sizes": [
				1
			],
			"type": "shader",
			"inputs": [
				{
					"name": "vertexPosition",
					"type": "vec3"
				},
				{
					"name": "texPosition",
					"type": "vec2"
				},
				{
					"name": "gl_VertexID",
					"type": "int"
				},
				{
					"name": "gl_InstanceID",
					"type": "int"
				}
			],
			"outputs": [
				{
					"name": "texCoord",
					"type": "vec2"
				}
			],
			"uniforms": [
				{
					"name": "projectionMatrix",
					"type": "mat4"
				}
			],
			"types": [
				{
					"name": "gl_PerVertex",
					"members": [
						{
							"type": "vec4",
							"name": "gl_Position"
						},
						{
							"type": "float",
							"name": "gl_PointSize"
						},
						{
							"type": "float[]",
							"name": "gl_ClipDistance"
						},
						{
							"type": "float[]",
							"name": "gl_CullDistance"
						}
					]
				}
			]
		},
		{
			"name": "simple_frag",
			"files": [
				"simple.frag.essl",
				"simple-webgl2.frag.essl"
			],
			"file_sizes": [
				1
			],
			"type": "shader",
			"inputs": [
				{
					"name": "texCoord",
					"type": "vec2"
				}
			],
			"outputs": [
				{
					"name": "FragColor",
					"type": "vec4"
				}
			],
			"uniforms": [
				{
					"name": "tex",
					"type": "sampler2D"
				}
			],
			"types": []
		},
		{
			"name": "simple_vert",
			"files": [
				"simple.vert.essl",
				"simple-webgl2.vert.essl"
			],
			"file_sizes": [
				1
			],
			"type": "shader",
			"inputs": [
				{
					"name": "vertexPosition",
					"type": "vec3"
				},
				{
					"name": "texPosition",
					"type": "vec2"
				},
				{
					"name": "gl_VertexID",
					"type": "int"
				},
				{
					"name": "gl_InstanceID",
					"type": "int"
				}
			],
			"outputs": [
				{
					"name": "texCoord",
					"type": "vec2"
				}
			],
			"uniforms": [
				{
					"name": "projectionMatrix",
					"type": "mat4"
				}
			],
			"types": [
				{
					"name": "gl_PerVertex",
					"members": [
						{
							"type": "vec4",
							"name": "gl_Position"
						},
						{
							"type": "float",
							"name": "gl_PointSize"
						},
						{
							"type": "float[]",
							"name": "gl_ClipDistance"
						},
						{
							"type": "float[]",
							"name": "gl_CullDistance"
						}
					]
				}
			]
		},
		{
			"name": "vBlurVertexShader_vert",
			"files": [
				"vBlurVertexShader.vert.essl",
				"vBlurVertexShader-webgl2.vert.essl"
			],
			"file_sizes": [
				1
			],
			"type": "shader",
			"inputs": [
				{
					"name": "vertexPosition",
					"type": "vec3"
				},
				{
					"name": "texPosition",
					"type": "vec2"
				},
				{
					"name": "gl_VertexID",
					"type": "int"
				},
				{
					"name": "gl_InstanceID",
					"type": "int"
				}
			],
			"outputs": [
				{
					"name": "v_texCoord",
					"type": "vec2"
				},
				{
					"name": "v_blurCoord0",
					"type": "vec2"
				},
				{
					"name": "v_blurCoord1",
					"type": "vec2"
				},
				{
					"name": "v_blurCoord2",
					"type": "vec2"
				},
				{
					"name": "v_blurCoord3",
					"type": "vec2"
				},
				{
					"name": "v_blurCoord4",
					"type": "vec2"
				},
				{
					"name": "v_blurCoord5",
					"type": "vec2"
				}
			],
			"uniforms": [
				{
					"name": "projectionMatrix",
					"type": "mat4"
				}
			],
			"types": [
				{
					"name": "gl_PerVertex",
					"members": [
						{
							"type": "vec4",
							"name": "gl_Position"
						},
						{
							"type": "float",
							"name": "gl_PointSize"
						},
						{
							"type": "float[]",
							"name": "gl_ClipDistance"
						},
						{
							"type": "float[]",
							"name": "gl_CullDistance"
						}
					]
				}
			]
		}
	]
}